CHANGELOGS.md
LICENSE.txt
MANIFEST.in
README.md
VERSION
setup.cfg
setup.py
examples/crud.py
examples/example.txt
leapcell/__init__.py
leapcell/const.py
leapcell/core.py
leapcell/exp.py
leapcell/field_item.py
leapcell/field_meta.py
leapcell/file.py
leapcell/http_client.py
leapcell/record.py
leapcell/table.py
leapcell/table_meta.py
leapcell/utils.py
leapcell/version.py
leapcell.egg-info/PKG-INFO
leapcell.egg-info/SOURCES.txt
leapcell.egg-info/dependency_links.txt
leapcell.egg-info/requires.txt
leapcell.egg-info/top_level.txt